demo/__init__.py
demo/feature_overview/__init__.py
demo/feature_overview/missing_embeddings.py
demo/feature_overview/no_missing_embeddings.py
example_pipelines/__init__.py
example_pipelines/_pipelines.py
example_pipelines/adult_complex/__init__.py
example_pipelines/adult_complex/adult_complex.py
example_pipelines/adult_simple/__init__.py
example_pipelines/adult_simple/adult_simple.py
example_pipelines/compas/__init__.py
example_pipelines/compas/compas.py
example_pipelines/healthcare/__init__.py
example_pipelines/healthcare/healthcare.py
example_pipelines/healthcare/healthcare_utils.py
experiments/__init__.py
experiments/performance/__init__.py
experiments/performance/_benchmark_utils.py
experiments/performance/_empty_inspection.py
experiments/user_interviews/__init__.py
experiments/user_interviews/adult_simple_modified.py
experiments/user_interviews/compas_modified.py
mlinspect/__init__.py
mlinspect/_inspector_result.py
mlinspect/_pipeline_inspector.py
mlinspect/backends/__init__.py
mlinspect/backends/_all_backends.py
mlinspect/backends/_backend.py
mlinspect/backends/_backend_utils.py
mlinspect/backends/_iter_creation.py
mlinspect/backends/_pandas_backend.py
mlinspect/backends/_pandas_backend_frame_wrapper.py
mlinspect/backends/_pandas_wir_processor.py
mlinspect/backends/_sklearn_backend.py
mlinspect/backends/_sklearn_backend_csr_matrx_wrapper.py
mlinspect/backends/_sklearn_backend_ndarray_wrapper.py
mlinspect/backends/_sklearn_backend_transformer_wrapper.py
mlinspect/backends/_sklearn_dag_processor.py
mlinspect/backends/_sklearn_wir_processor.py
mlinspect/checks/__init__.py
mlinspect/checks/_check.py
mlinspect/checks/_no_bias_introduced_for.py
mlinspect/checks/_no_illegal_features.py
mlinspect/inspections/__init__.py
mlinspect/inspections/_histogram_for_columns.py
mlinspect/inspections/_inspection.py
mlinspect/inspections/_inspection_input.py
mlinspect/inspections/_inspection_result.py
mlinspect/inspections/_lineage.py
mlinspect-0.0.1.dev0.dist-info/LICENSE
mlinspect-0.0.1.dev0.dist-info/METADATA
mlinspect-0.0.1.dev0.dist-info/WHEEL
mlinspect-0.0.1.dev0.dist-info/top_level.txt
mlinspect-0.0.1.dev0.dist-info/RECORD
